MANIFEST.in
README.rst
setup.py
gtoolbox/__init__.py
gtoolbox/mylogger.py
gtoolbox/utilities.py
gtoolbox.egg-info/PKG-INFO
gtoolbox.egg-info/SOURCES.txt
gtoolbox.egg-info/dependency_links.txt
gtoolbox.egg-info/requires.txt
gtoolbox.egg-info/top_level.txt
gtoolbox.egg-info/zip-safe