Metadata-Version: 1.0
Name: gtoolbox
Version: 1.0
Summary: donehandler;logger;Region
Home-page: https://pypi.python.org/pypi/gtoolbox
Author: kandit
Author-email: girichev@planet.iitp.ru
License: MIT
Platform: UNKNOWN
